lab_3/processor.v
`timescale 1ns / 1ps

// ======================================================
// 1. Instruction Memory
// ======================================================

module instruction_memory(
    input  wire [7:0]  pc,
    output wire [15:0] inst
);

    reg [15:0] memory [0:255];
    integer i;

    // Opcode definitions
    localparam OP_ADD = 4'b0000;
    localparam OP_SUB = 4'b0001;
    localparam OP_AND = 4'b0010;
    localparam OP_OR  = 4'b0011;
    localparam OP_XOR = 4'b0100;
    localparam OP_INC = 4'b0101;
    localparam OP_DEC = 4'b0110;
    localparam OP_CMP = 4'b0111;
    localparam OP_LDI = 4'b1000;
    localparam OP_NOP = 4'b1111;

    initial begin
        // Default all memory locations as NOP
        for (i = 0; i < 256; i = i + 1) begin
            memory[i] = {OP_NOP, 12'b0};
        end

        // Example program

        // LDI R1, 5
        // Format: opcode, write_reg, unused, immediate
        memory[0] = {OP_LDI, 3'd1, 1'b0, 8'd5};

        // LDI R2, 3
        memory[1] = {OP_LDI, 3'd2, 1'b0, 8'd3};

        // ADD R3, R1, R2
        // R3 = R1 + R2
        memory[2] = {OP_ADD, 3'd3, 3'd1, 3'd2, 3'b000};

        // SUB R4, R1, R2
        // R4 = R1 - R2
        memory[3] = {OP_SUB, 3'd4, 3'd1, 3'd2, 3'b000};

        // AND R5, R1, R2
        memory[4] = {OP_AND, 3'd5, 3'd1, 3'd2, 3'b000};

        // OR R6, R1, R2
        memory[5] = {OP_OR, 3'd6, 3'd1, 3'd2, 3'b000};

        // XOR R7, R1, R2
        memory[6] = {OP_XOR, 3'd7, 3'd1, 3'd2, 3'b000};
    end

    // Instruction output based on current PC
    assign inst = memory[pc];

endmodule


// ======================================================
// 2. Control Unit
// ======================================================

module control_unit(
    input  wire        clk,
    input  wire        rst,
    input  wire [15:0] inst,

    output reg  [7:0]  pc,

    // Register file controls
    output reg  [2:0]  read_reg1,
    output reg  [2:0]  read_reg2,
    output reg  [2:0]  write_reg,
    output reg         write_enable,

    // Datapath controls
    output reg  [7:0]  immediate,
    output reg         sel_2s_comp,
    output reg         sel_operand1,

    // ALU control
    output reg  [2:0]  alu_op
);

    // Opcode definitions
    localparam OP_ADD = 4'b0000;
    localparam OP_SUB = 4'b0001;
    localparam OP_AND = 4'b0010;
    localparam OP_OR  = 4'b0011;
    localparam OP_XOR = 4'b0100;
    localparam OP_INC = 4'b0101;
    localparam OP_DEC = 4'b0110;
    localparam OP_CMP = 4'b0111;
    localparam OP_LDI = 4'b1000;
    localparam OP_NOP = 4'b1111;

    // Program Counter
    always @(posedge clk or posedge rst) begin
        if (rst)
            pc <= 8'd0;
        else
            pc <= pc + 8'd1;
    end

    // Instruction Decode
    always @(*) begin
        // Default values
        read_reg1     = inst[8:6];
        read_reg2     = inst[5:3];
        write_reg     = inst[11:9];
        immediate     = inst[7:0];

        write_enable  = 1'b0;
        sel_2s_comp   = 1'b0;
        sel_operand1  = 1'b0;
        alu_op        = 3'b000;

        case (inst[15:12])

            OP_ADD: begin
                alu_op       = 3'b000;
                write_enable = 1'b1;
            end

            OP_SUB: begin
                alu_op       = 3'b001;
                sel_2s_comp  = 1'b1;
                write_enable = 1'b1;
            end

            OP_AND: begin
                alu_op       = 3'b010;
                write_enable = 1'b1;
            end

            OP_OR: begin
                alu_op       = 3'b011;
                write_enable = 1'b1;
            end

            OP_XOR: begin
                alu_op       = 3'b100;
                write_enable = 1'b1;
            end

            OP_INC: begin
                alu_op       = 3'b101;
                write_enable = 1'b1;
            end

            OP_DEC: begin
                alu_op       = 3'b110;
                write_enable = 1'b1;
            end

            OP_CMP: begin
                alu_op       = 3'b111;
                sel_2s_comp  = 1'b1;
                write_enable = 1'b0;
            end

            OP_LDI: begin
                // Load immediate into register
                alu_op       = 3'b000;
                sel_operand1 = 1'b1;
                write_enable = 1'b1;

                // Immediate instruction does not need register read
                read_reg1    = 3'd0;
                read_reg2    = 3'd0;
            end

            OP_NOP: begin
                write_enable = 1'b0;
            end

            default: begin
                write_enable = 1'b0;
            end

        endcase
    end

endmodule


// ======================================================
// 3. 8 x 8 Register File
// ======================================================

module register_file_8x8(
    input  wire       clk,
    input  wire       rst,

    input  wire [2:0] read_reg1,
    input  wire [2:0] read_reg2,
    input  wire [2:0] write_reg,

    input  wire [7:0] write_data,
    input  wire       write_enable,

    output wire [7:0] regout1,
    output wire [7:0] regout2
);

    reg [7:0] regs [0:7];
    integer i;

    // Asynchronous read
    assign regout1 = regs[read_reg1];
    assign regout2 = regs[read_reg2];

    // Synchronous write
    always @(posedge clk or posedge rst) begin
        if (rst) begin
            for (i = 0; i < 8; i = i + 1) begin
                regs[i] <= 8'd0;
            end
        end
        else begin
            if (write_enable) begin
                regs[write_reg] <= write_data;
            end
        end
    end

endmodule


// ======================================================
// 4. Top Module: Control Unit + Instruction Memory + Register File
// ======================================================

module processor_frontend_8bit(
    input  wire       clk,
    input  wire       rst,

    // This will come from ALU later
    input  wire [7:0] alu_result,

    output wire [7:0]  pc,
    output wire [15:0] inst,

    output wire [2:0]  read_reg1,
    output wire [2:0]  read_reg2,
    output wire [2:0]  write_reg,
    output wire        write_enable,

    output wire [7:0]  immediate,
    output wire        sel_2s_comp,
    output wire        sel_operand1,
    output wire [2:0]  alu_op,

    output wire [7:0]  regout1,
    output wire [7:0]  regout2,

    // Outputs going toward ALU
    output wire [7:0]  operand1,
    output wire [7:0]  operand2
);

    localparam OP_LDI = 4'b1000;

    wire [7:0] regout2_2s_comp;
    wire [7:0] register_write_data;

    // Instruction Memory
    instruction_memory imem (
        .pc(pc),
        .inst(inst)
    );

    // Control Unit
    control_unit cu (
        .clk(clk),
        .rst(rst),
        .inst(inst),
        .pc(pc),

        .read_reg1(read_reg1),
        .read_reg2(read_reg2),
        .write_reg(write_reg),
        .write_enable(write_enable),

        .immediate(immediate),
        .sel_2s_comp(sel_2s_comp),
        .sel_operand1(sel_operand1),

        .alu_op(alu_op)
    );

    // 2's complement unit
    assign regout2_2s_comp = (~regout2) + 8'd1;

    // Operand selection
    assign operand1 = (sel_operand1) ? immediate : regout1;
    assign operand2 = (sel_2s_comp)  ? regout2_2s_comp : regout2;

    // For LDI instruction, write immediate directly.
    // For other instructions, write ALU result.
    assign register_write_data = (inst[15:12] == OP_LDI) ? immediate : alu_result;

    // Register File
    register_file_8x8 rf (
        .clk(clk),
        .rst(rst),

        .read_reg1(read_reg1),
        .read_reg2(read_reg2),
        .write_reg(write_reg),

        .write_data(register_write_data),
        .write_enable(write_enable),

        .regout1(regout1),
        .regout2(regout2)
    );

endmodule

lab_3/processor_tb.v
`timescale 1ns / 1ps

module processor_frontend_comprehensive_tb;

    reg clk;
    reg rst;

    reg [7:0] alu_result;

    wire [7:0]  pc;
    wire [15:0] inst;

    wire [2:0] read_reg1;
    wire [2:0] read_reg2;
    wire [2:0] write_reg;
    wire       write_enable;

    wire [7:0] immediate;
    wire       sel_2s_comp;
    wire       sel_operand1;
    wire [2:0] alu_op;

    wire [7:0] regout1;
    wire [7:0] regout2;

    wire [7:0] operand1;
    wire [7:0] operand2;

    // Instantiate processor front-end
    processor_frontend_8bit uut (
        .clk(clk),
        .rst(rst),
        .alu_result(alu_result),
        .pc(pc),
        .inst(inst),
        .read_reg1(read_reg1),
        .read_reg2(read_reg2),
        .write_reg(write_reg),
        .write_enable(write_enable),
        .immediate(immediate),
        .sel_2s_comp(sel_2s_comp),
        .sel_operand1(sel_operand1),
        .alu_op(alu_op),
        .regout1(regout1),
        .regout2(regout2),
        .operand1(operand1),
        .operand2(operand2)
    );

    // Clock generation (10ns period)
    initial begin
        clk = 0;
        forever #5 clk = ~clk;
    end

    // Behavioral ALU model for testbench execution
    always @(*) begin
        case (alu_op)
            3'b000: alu_result = operand1 + operand2; // ADD / LDI fallback
            3'b001: alu_result = operand1 + operand2; // SUB (operand2 is 2's complement)
            3'b010: alu_result = operand1 & operand2; // AND
            3'b011: alu_result = operand1 | operand2; // OR
            3'b100: alu_result = operand1 ^ operand2; // XOR
            3'b101: alu_result = operand1 + 8'd1;     // INC
            3'b110: alu_result = operand1 - 8'd1;     // DEC
            3'b111: alu_result = operand1 + operand2; // CMP (subtracts via 2's comp)
            default: alu_result = 8'd0;
        endcase
    end

    // Test stimulus and verification block
    initial begin
        $dumpfile("processor_frontend_comprehensive_tb.vcd");
        $dumpvars(1, processor_frontend_comprehensive_tb);

        $display("=================================================================================================");
        $display(" TIME  | PC | INSTRUCTION      | WE | WR | R1 | R2 | OP1 | OP2 | ALU_RES | R1  R2  R3  R4  R5  R6  R7 ");
        $display("=================================================================================================");

        // Apply Reset
        rst = 1;
        #12;
        rst = 0;

        // Run simulation for enough cycles to execute the example instruction block
        #100;

        $display("=================================================================================================");
        $display("SIMULATION COMPLETE: Final Register States Verified.");
        $display("R1 = %0d (Expected: 5)", uut.rf.regs[1]);
        $display("R2 = %0d (Expected: 3)", uut.rf.regs[2]);
        $display("R3 = %0d (Expected: 8)", uut.rf.regs[3]);
        $display("R4 = %0d (Expected: 2)", uut.rf.regs[4]);
        $display("R5 = %0d (Expected: 1)", uut.rf.regs[5]);
        $display("R6 = %0d (Expected: 7)", uut.rf.regs[6]);
        $display("R7 = %0d (Expected: 6)", uut.rf.regs[7]);
        $display("=================================================================================================");

        $finish;
    end

    // Real-time monitoring log
    always @(posedge clk) begin
        #1; // Sample shortly after rising edge for stable outputs
        $display("%5t  | %2d | %16b |  %b | R%0d | R%0d | R%0d | %3d | %3d |   %3d   | %3d %3d %3d %3d %3d %3d %3d",
            $time,
            pc,
            inst,
            write_enable,
            write_reg,
            read_reg1,
            read_reg2,
            operand1,
            operand2,
            alu_result,
            uut.rf.regs[1],
            uut.rf.regs[2],
            uut.rf.regs[3],
            uut.rf.regs[4],
            uut.rf.regs[5],
            uut.rf.regs[6],
            uut.rf.regs[7]
        );
    end

endmodule

lab_3/processor_frontend_comprehensive_tb.vcd
$date
	Tue Jul 28 11:56:57 2026
$end
$version
	Icarus Verilog
$end
$timescale
	1ps
$end
$scope module processor_frontend_comprehensive_tb $end
$var wire 3 ! write_reg [2:0] $end
$var wire 1 " write_enable $end
$var wire 1 # sel_operand1 $end
$var wire 1 $ sel_2s_comp $end
$var wire 8 % regout2 [7:0] $end
$var wire 8 & regout1 [7:0] $end
$var wire 3 ' read_reg2 [2:0] $end
$var wire 3 ( read_reg1 [2:0] $end
$var wire 8 ) pc [7:0] $end
$var wire 8 * operand2 [7:0] $end
$var wire 8 + operand1 [7:0] $end
$var wire 16 , inst [15:0] $end
$var wire 8 - immediate [7:0] $end
$var wire 3 . alu_op [2:0] $end
$var reg 8 / alu_result [7:0] $end
$var reg 1 0 clk $end
$var reg 1 1 rst $end
$upscope $end
$enddefinitions $end
$comment Show the parameter values. $end
$dumpall
$end
#0
$dumpvars
11
00
b101 /
b0 .
b101 -
b1000001000000101 ,
b101 +
b0 *
b0 )
b0 (
b0 '
b0 &
b0 %
0$
1#
1"
b1 !
$end
#5000
10
#10000
00
#12000
01
#15000
b11 /
b11 +
1#
1"
b11 -
b10 !
b1000010000000011 ,
b1 )
10
#20000
00
#25000
b1000 /
b11 *
b101 +
b11 %
b101 &
0#
1"
b1010000 -
b11 !
b10 '
b1 (
b11001010000 ,
b10 )
10
#30000
00
#35000
b10 /
b11111101 *
1$
b1 .
1"
b100 !
b1100001010000 ,
b11 )
10
#40000
00
#45000
b1 /
b11 *
b10 .
0$
1"
b101 !
b10101001010000 ,
b100 )
10
#50000
00
#55000
b111 /
b11 .
1"
b110 !
b11110001010000 ,
b101 )
10
#60000
00
#65000
b110 /
b100 .
1"
b111 !
b100111001010000 ,
b110 )
10
#70000
00
#75000
b0 *
b0 +
b0 /
b0 %
b0 &
b0 .
0"
b0 -
b0 !
b0 '
b0 (
b1111000000000000 ,
b111 )
10
#80000
00
#85000
b1000 )
10
#90000
00
#95000
b1001 )
10
#100000
00
#105000
b1010 )
10
